peaq_msf/__init__.py
peaq_msf/base.py
peaq_msf/machine_station.py
peaq_msf/main.py
peaq_msf/abi/__init__.py
peaq_msf/abi/errors_abi.json
peaq_msf/abi/events_abi.json
peaq_msf/abi/msf_abi.json
peaq_msf/types/__init__.py
peaq_msf/types/base.py
peaq_msf/types/common.py
peaq_msf/types/machine_station.py
peaq_msf/utils/__init__.py
peaq_msf/utils/evm_log_decoder.py
peaq_msf/utils/utils.py
peaq_msf-1.0.2.dist-info/METADATA
peaq_msf-1.0.2.dist-info/WHEEL
peaq_msf-1.0.2.dist-info/top_level.txt
peaq_msf-1.0.2.dist-info/RECORD
