Metadata-Version: 2.4
Name: peaq-msf
Version: 1.0.2
Summary: Peaq Network SDK for DID, Storage, RBAC operations, and blockchain interactions
Home-page: https://github.com/peaq-network/peaq-py/
Author: Peaq Network
Author-email: info@peaq.network
License: MIT
Classifier: Programming Language :: Python :: 3
Classifier: Programming Language :: Python :: 3.8
Classifier: Programming Language :: Python :: 3.9
Classifier: Programming Language :: Python :: 3.10
Classifier: Programming Language :: Python :: 3.11
Classifier: Programming Language :: Python :: 3.12
Classifier: Operating System :: OS Independent
Requires-Python: >=3.8
Requires-Dist: web3>=7.10.0
